pgstacrs-0.1.1.dist-info/METADATA
pgstacrs-0.1.1.dist-info/WHEEL
pgstacrs-0.1.1.dist-info/licenses/LICENSE
pgstacrs/__init__.py
pgstacrs/__init__.pyi
pgstacrs/py.typed
pgstacrs/pgstacrs.cp311-win32.pyd
pgstacrs-0.1.1.dist-info/RECORD
