Metadata-Version: 2.4
Name: pgstacrs
Version: 0.1.1
Classifier: Programming Language :: Rust
Classifier: Programming Language :: Python :: Implementation :: CPython
Classifier: Programming Language :: Python :: Implementation :: PyPy
License-File: LICENSE
Summary: Python async API for pgstac, backed by Rust
Keywords: stac,geospatial,postgres,pgstac
Author-email: Pete Gadomski <pete.gadomski@gmail.com>
Requires-Python: >=3.9
Project-URL: Github, https://github.com/stac-utils/pgstacrs
Project-URL: Docs, https://stac-utils.github.io/pgstacrs/
Project-URL: Issues, https://github.com/stac-utils/pgstacrs/issues
